proglearn/__init__.py
proglearn/base.py
proglearn/deciders.py
proglearn/forest.py
proglearn/network.py
proglearn/progressive_learner.py
proglearn/transformers.py
proglearn/voters.py
proglearn/sims/__init__.py
proglearn/sims/gaussian_sim.py
proglearn/sims/spiral_sim.py
proglearn/tests/__init__.py
proglearn/tests/test_forest.py
proglearn/tests/test_network.py
proglearn/tests/test_system.py
proglearn/tests/test_transformer.py
proglearn/tests/test_voter.py
proglearn-0.0.7.dist-info/LICENSE
proglearn-0.0.7.dist-info/METADATA
proglearn-0.0.7.dist-info/WHEEL
proglearn-0.0.7.dist-info/top_level.txt
proglearn-0.0.7.dist-info/RECORD
