Metadata-Version: 2.1
Name: proglearn
Version: 0.0.7
Summary: A package to implement and extend the methods desribed in 'Omnidirectional Transfer for Quasilinear Lifelong Learning'
Home-page: https://github.com/neurodata/ProgLearn/
Author: Will LeVine, Jayanta Dey, Hayden Helm
Author-email: levinewill@icloud.com
Maintainer: Jayanta Dey, Haoyin Xu
Maintainer-email: jdey4@jhmi.edu
License: MIT
Platform: UNKNOWN
Classifier: Intended Audience :: Science/Research
Classifier: Topic :: Scientific/Engineering :: Mathematics
Classifier: License :: OSI Approved :: MIT License
Classifier: Programming Language :: Python :: 3
Classifier: Programming Language :: Python :: 3.6
Classifier: Programming Language :: Python :: 3.7
Classifier: Programming Language :: Python :: 3.8
Classifier: Programming Language :: Python :: 3.9
License-File: LICENSE
Requires-Dist: tensorflow (>=1.19.0)
Requires-Dist: scikit-learn (>=0.22.0)
Requires-Dist: scipy (>=1.4.1)
Requires-Dist: joblib (>=0.14.1)
Requires-Dist: numpy (>=1.19.2)
